noop.cpython-311-x86_64-linux-gnu.so
sqlite_xsv/__init__.py
sqlite_xsv/xsv0.so
sqlite_xsv-0.2.0.dist-info/METADATA
sqlite_xsv-0.2.0.dist-info/WHEEL
sqlite_xsv-0.2.0.dist-info/top_level.txt
sqlite_xsv-0.2.0.dist-info/RECORD
