Metadata-Version: 2.1
Name: sqlite-xsv
Version: 0.2.0
Home-page: https://github.com/asg017/sqlite-xsv
Author: Alex Garcia
License: MIT License, Apache License, Version 2.0
Project-URL: Issues, https://github.com/asg017/sqlite-xsv/issues
Project-URL: CI, https://github.com/asg017/sqlite-xsv/actions
Project-URL: Changelog, https://github.com/asg017/sqlite-xsv/releases
Requires-Python: >=3.7
Provides-Extra: test
Requires-Dist: pytest ; extra == 'test'
